brinias/__init__.py
brinias/api.py
brinias/core.py
brinias/file_utils.py
brinias_engine-0.1.1.dist-info/METADATA
brinias_engine-0.1.1.dist-info/WHEEL
brinias_engine-0.1.1.dist-info/top_level.txt
brinias_engine-0.1.1.dist-info/RECORD
