Metadata-Version: 2.4
Name: brinias-engine
Version: 0.1.1
Summary: Brinias: A symbolic regression and classification tool using Genetic Programming.
Home-page: https://github.com/brinias/brinias
Author: Konstantinos Brinias
Author-email: brinias2@gmail.com
Classifier: Programming Language :: Python :: 3
Classifier: License :: OSI Approved :: MIT License
Classifier: Operating System :: OS Independent
Requires-Python: >=3.7
Requires-Dist: pandas
Requires-Dist: numpy
Requires-Dist: scikit-learn
Requires-Dist: deap
Requires-Dist: matplotlib
Dynamic: author
Dynamic: author-email
Dynamic: classifier
Dynamic: description
Dynamic: description-content-type
Dynamic: home-page
Dynamic: requires-dist
Dynamic: requires-python
Dynamic: summary
